stanza/__init__.py
stanza/_version.py
stanza/models/__init__.py
stanza/models/_training_logging.py
stanza/models/charlm.py
stanza/models/classifier.py
stanza/models/constituency_parser.py
stanza/models/identity_lemmatizer.py
stanza/models/lang_identifier.py
stanza/models/lemmatizer.py
stanza/models/mwt_expander.py
stanza/models/ner_tagger.py
stanza/models/parser.py
stanza/models/tagger.py
stanza/models/tokenizer.py
stanza/models/wl_coref.py
stanza/models/classifiers/__init__.py
stanza/models/classifiers/base_classifier.py
stanza/models/classifiers/cnn_classifier.py
stanza/models/classifiers/config.py
stanza/models/classifiers/constituency_classifier.py
stanza/models/classifiers/data.py
stanza/models/classifiers/iterate_test.py
stanza/models/classifiers/trainer.py
stanza/models/classifiers/utils.py
stanza/models/common/__init__.py
stanza/models/common/beam.py
stanza/models/common/bert_embedding.py
stanza/models/common/biaffine.py
stanza/models/common/build_short_name_to_treebank.py
stanza/models/common/char_model.py
stanza/models/common/chuliu_edmonds.py
stanza/models/common/constant.py
stanza/models/common/convert_pretrain.py
stanza/models/common/count_ner_coverage.py
stanza/models/common/count_pretrain_coverage.py
stanza/models/common/crf.py
stanza/models/common/data.py
stanza/models/common/doc.py
stanza/models/common/dropout.py
stanza/models/common/exceptions.py
stanza/models/common/foundation_cache.py
stanza/models/common/hlstm.py
stanza/models/common/large_margin_loss.py
stanza/models/common/loss.py
stanza/models/common/maxout_linear.py
stanza/models/common/packed_lstm.py
stanza/models/common/peft_config.py
stanza/models/common/pretrain.py
stanza/models/common/relative_global_attn.py
stanza/models/common/seq2seq_constant.py
stanza/models/common/seq2seq_model.py
stanza/models/common/seq2seq_modules.py
stanza/models/common/seq2seq_utils.py
stanza/models/common/short_name_to_treebank.py
stanza/models/common/stanza_object.py
stanza/models/common/trainer.py
stanza-1.10.0.dist-info/LICENSE
stanza-1.10.0.dist-info/METADATA
stanza-1.10.0.dist-info/WHEEL
stanza-1.10.0.dist-info/top_level.txt
stanza-1.10.0.dist-info/RECORD
