Metadata-Version: 2.1
Name: stanza
Version: 1.10.0
Summary: A Python NLP Library for Many Human Languages, by the Stanford NLP Group
Home-page: https://github.com/stanfordnlp/stanza
Author: Stanford Natural Language Processing Group
Author-email: jebolton@stanford.edu
License: Apache License 2.0
Keywords: natural-language-processing nlp natural-language-understanding stanford-nlp deep-learning
Classifier: Development Status :: 4 - Beta
Classifier: Intended Audience :: Developers
Classifier: Intended Audience :: Education
Classifier: Intended Audience :: Science/Research
Classifier: Intended Audience :: Information Technology
Classifier: Topic :: Scientific/Engineering
Classifier: Topic :: Scientific/Engineering :: Artificial Intelligence
Classifier: Topic :: Scientific/Engineering :: Information Analysis
Classifier: Topic :: Text Processing
Classifier: Topic :: Text Processing :: Linguistic
Classifier: Topic :: Software Development
Classifier: Topic :: Software Development :: Libraries
Classifier: Programming Language :: Python :: 3.8
Classifier: Programming Language :: Python :: 3.9
Classifier: Programming Language :: Python :: 3.10
Classifier: Programming Language :: Python :: 3.11
Classifier: Programming Language :: Python :: 3.12
Requires-Python: >=3.8
License-File: LICENSE
Requires-Dist: emoji
Requires-Dist: numpy
Requires-Dist: protobuf>=3.15.0
Requires-Dist: requests
Requires-Dist: networkx
Requires-Dist: tomli; python_version < "3.11"
Requires-Dist: torch>=1.3.0
Requires-Dist: tqdm
Provides-Extra: dev
Requires-Dist: check-manifest; extra == "dev"
Provides-Extra: test
Requires-Dist: coverage; extra == "test"
Requires-Dist: pytest; extra == "test"
Provides-Extra: transformers
Requires-Dist: transformers>=3.0.0; extra == "transformers"
Requires-Dist: peft>=0.6.1; extra == "transformers"
Provides-Extra: datasets
Requires-Dist: datasets; extra == "datasets"
Provides-Extra: tokenizers
Requires-Dist: jieba; extra == "tokenizers"
Requires-Dist: pythainlp; extra == "tokenizers"
Requires-Dist: python-crfsuite; extra == "tokenizers"
Requires-Dist: spacy; extra == "tokenizers"
Requires-Dist: sudachidict_core; extra == "tokenizers"
Requires-Dist: sudachipy; extra == "tokenizers"
Provides-Extra: visualization
Requires-Dist: spacy; extra == "visualization"
Requires-Dist: streamlit; extra == "visualization"
Requires-Dist: ipython; extra == "visualization"
